pyidw/__init__.py
pyidw/idw.py
pyidw-0.0.2.dist-info/LICENSE
pyidw-0.0.2.dist-info/METADATA
pyidw-0.0.2.dist-info/WHEEL
pyidw-0.0.2.dist-info/top_level.txt
pyidw-0.0.2.dist-info/RECORD
